SpeechToText_STT/__init__.py
SpeechToTextSTT-1.0.dist-info/METADATA
SpeechToTextSTT-1.0.dist-info/WHEEL
SpeechToTextSTT-1.0.dist-info/top_level.txt
SpeechToTextSTT-1.0.dist-info/RECORD
